Metadata-Version: 1.0
Name: geonode-datastore-shards
Version: 0.1
Summary: GeoNode Datastore Shard Application
Home-page: http://geonode.org
Author: GeoNode Developers
Author-email: dev@geonode.org
License: GPL
Platform: UNKNOWN
